sjkabc/__init__.py
sjkabc/sjkabc.py
sjkabc-1.4.2.dist-info/METADATA
sjkabc-1.4.2.dist-info/WHEEL
sjkabc-1.4.2.dist-info/RECORD
