Metadata-Version: 2.1
Name: sjkabc
Version: 1.4.2
Summary: ABC music notation parsing library.
Project-URL: Source, https://github.com/sjktje/sjkabc
Project-URL: Documentation, https://readthedocs.org/projects/sjkabc/
Author-email: Svante Kvarnström <sjk@sjk.io>
License: BSD
Classifier: Development Status :: 4 - Beta
Classifier: License :: OSI Approved :: BSD License
Classifier: Programming Language :: Python :: 3
